[
    {
        "values": [
            [
                "1976", 
                "0.0"
            ], 
            [
                "1977", 
                "0.3333333333333333"
            ], 
            [
                "1978", 
                "0.0"
            ], 
            [
                "1980", 
                "0.0"
            ], 
            [
                "1981", 
                "0.0"
            ], 
            [
                "1982", 
                "0.2"
            ], 
            [
                "1983", 
                "1.457142857142857"
            ], 
            [
                "1985", 
                "0.0"
            ], 
            [
                "1986", 
                "0.0"
            ], 
            [
                "1987", 
                "0.0"
            ], 
            [
                "1988", 
                "0.0"
            ], 
            [
                "1990", 
                "0.0"
            ], 
            [
                "1991", 
                "0.0"
            ], 
            [
                "1992", 
                "0.4"
            ], 
            [
                "1993", 
                "0.0"
            ], 
            [
                "1995", 
                "0.0"
            ], 
            [
                "1997", 
                "0.0"
            ], 
            [
                "1998", 
                "0.0"
            ], 
            [
                "2002", 
                "0.0"
            ], 
            [
                "2004", 
                "0.0"
            ], 
            [
                "2005", 
                "0.0"
            ], 
            [
                "2006", 
                "0.0"
            ], 
            [
                "2007", 
                "0.0"
            ], 
            [
                "2008", 
                "0.6666666666666666"
            ], 
            [
                "2009", 
                "0.0"
            ], 
            [
                "2010", 
                "0.0"
            ], 
            [
                "2011", 
                "0.0"
            ], 
            [
                "2012", 
                "0.0"
            ], 
            [
                "2013", 
                "0.47619047619047616"
            ], 
            [
                "2014", 
                "0.0"
            ]
        ], 
        "key": "Topic 00"
    }, 
    {
        "values": [
            [
                "1976", 
                "0.0"
            ], 
            [
                "1977", 
                "0.0"
            ], 
            [
                "1978", 
                "0.0"
            ], 
            [
                "1980", 
                "0.0"
            ], 
            [
                "1981", 
                "0.0"
            ], 
            [
                "1982", 
                "0.0"
            ], 
            [
                "1983", 
                "0.0"
            ], 
            [
                "1985", 
                "0.0"
            ], 
            [
                "1986", 
                "0.0"
            ], 
            [
                "1987", 
                "0.0"
            ], 
            [
                "1988", 
                "0.0"
            ], 
            [
                "1990", 
                "0.0"
            ], 
            [
                "1991", 
                "0.0"
            ], 
            [
                "1992", 
                "0.0"
            ], 
            [
                "1993", 
                "0.0"
            ], 
            [
                "1995", 
                "0.0"
            ], 
            [
                "1997", 
                "0.0"
            ], 
            [
                "1998", 
                "0.0"
            ], 
            [
                "2002", 
                "1.0"
            ], 
            [
                "2004", 
                "0.0"
            ], 
            [
                "2005", 
                "0.0"
            ], 
            [
                "2006", 
                "0.0"
            ], 
            [
                "2007", 
                "0.8333333333333334"
            ], 
            [
                "2008", 
                "0.0"
            ], 
            [
                "2009", 
                "0.0"
            ], 
            [
                "2010", 
                "0.0"
            ], 
            [
                "2011", 
                "0.0"
            ], 
            [
                "2012", 
                "1.0"
            ], 
            [
                "2013", 
                "0.0"
            ], 
            [
                "2014", 
                "0.0"
            ]
        ], 
        "key": "Topic 01"
    }, 
    {
        "values": [
            [
                "1976", 
                "0.0"
            ], 
            [
                "1977", 
                "0.6666666666666666"
            ], 
            [
                "1978", 
                "0.0"
            ], 
            [
                "1980", 
                "0.0"
            ], 
            [
                "1981", 
                "0.0"
            ], 
            [
                "1982", 
                "0.0"
            ], 
            [
                "1983", 
                "0.14285714285714285"
            ], 
            [
                "1985", 
                "0.0"
            ], 
            [
                "1986", 
                "0.0"
            ], 
            [
                "1987", 
                "0.0"
            ], 
            [
                "1988", 
                "0.0"
            ], 
            [
                "1990", 
                "0.0"
            ], 
            [
                "1991", 
                "0.0"
            ], 
            [
                "1992", 
                "0.0"
            ], 
            [
                "1993", 
                "1.0"
            ], 
            [
                "1995", 
                "0.0"
            ], 
            [
                "1997", 
                "0.0"
            ], 
            [
                "1998", 
                "0.0"
            ], 
            [
                "2002", 
                "0.0"
            ], 
            [
                "2004", 
                "0.0"
            ], 
            [
                "2005", 
                "0.0"
            ], 
            [
                "2006", 
                "0.0"
            ], 
            [
                "2007", 
                "0.0"
            ], 
            [
                "2008", 
                "0.0"
            ], 
            [
                "2009", 
                "0.0"
            ], 
            [
                "2010", 
                "0.0"
            ], 
            [
                "2011", 
                "0.0"
            ], 
            [
                "2012", 
                "0.0"
            ], 
            [
                "2013", 
                "0.0"
            ], 
            [
                "2014", 
                "0.0"
            ]
        ], 
        "key": "Topic 02"
    }, 
    {
        "values": [
            [
                "1976", 
                "0.0"
            ], 
            [
                "1977", 
                "1.0"
            ], 
            [
                "1978", 
                "0.16666666666666666"
            ], 
            [
                "1980", 
                "0.0"
            ], 
            [
                "1981", 
                "0.0"
            ], 
            [
                "1982", 
                "0.0"
            ], 
            [
                "1983", 
                "0.0"
            ], 
            [
                "1985", 
                "0.0"
            ], 
            [
                "1986", 
                "0.0"
            ], 
            [
                "1987", 
                "0.0"
            ], 
            [
                "1988", 
                "0.0"
            ], 
            [
                "1990", 
                "0.0"
            ], 
            [
                "1991", 
                "1.0"
            ], 
            [
                "1992", 
                "0.0"
            ], 
            [
                "1993", 
                "0.0"
            ], 
            [
                "1995", 
                "0.0"
            ], 
            [
                "1997", 
                "1.0"
            ], 
            [
                "1998", 
                "0.0"
            ], 
            [
                "2002", 
                "0.0"
            ], 
            [
                "2004", 
                "0.0"
            ], 
            [
                "2005", 
                "0.0"
            ], 
            [
                "2006", 
                "0.0"
            ], 
            [
                "2007", 
                "0.0"
            ], 
            [
                "2008", 
                "0.0"
            ], 
            [
                "2009", 
                "0.0"
            ], 
            [
                "2010", 
                "0.2"
            ], 
            [
                "2011", 
                "0.0"
            ], 
            [
                "2012", 
                "0.0"
            ], 
            [
                "2013", 
                "1.0"
            ], 
            [
                "2014", 
                "0.0"
            ]
        ], 
        "key": "Topic 03"
    }, 
    {
        "values": [
            [
                "1976", 
                "0.0"
            ], 
            [
                "1977", 
                "0.0"
            ], 
            [
                "1978", 
                "0.0"
            ], 
            [
                "1980", 
                "0.0"
            ], 
            [
                "1981", 
                "0.0"
            ], 
            [
                "1982", 
                "0.5"
            ], 
            [
                "1983", 
                "0.0"
            ], 
            [
                "1985", 
                "0.0"
            ], 
            [
                "1986", 
                "0.0"
            ], 
            [
                "1987", 
                "0.0"
            ], 
            [
                "1988", 
                "0.0"
            ], 
            [
                "1990", 
                "0.0"
            ], 
            [
                "1991", 
                "0.0"
            ], 
            [
                "1992", 
                "0.0"
            ], 
            [
                "1993", 
                "0.0"
            ], 
            [
                "1995", 
                "0.0"
            ], 
            [
                "1997", 
                "0.0"
            ], 
            [
                "1998", 
                "0.0"
            ], 
            [
                "2002", 
                "0.0"
            ], 
            [
                "2004", 
                "0.0"
            ], 
            [
                "2005", 
                "0.0"
            ], 
            [
                "2006", 
                "0.0"
            ], 
            [
                "2007", 
                "0.0"
            ], 
            [
                "2008", 
                "1.0"
            ], 
            [
                "2009", 
                "0.3333333333333333"
            ], 
            [
                "2010", 
                "0.0"
            ], 
            [
                "2011", 
                "0.0"
            ], 
            [
                "2012", 
                "0.0"
            ], 
            [
                "2013", 
                "0.0"
            ], 
            [
                "2014", 
                "1.0"
            ]
        ], 
        "key": "Topic 04"
    }, 
    {
        "values": [
            [
                "1976", 
                "0.2"
            ], 
            [
                "1977", 
                "0.0"
            ], 
            [
                "1978", 
                "1.6666666666666665"
            ], 
            [
                "1980", 
                "0.0"
            ], 
            [
                "1981", 
                "0.0"
            ], 
            [
                "1982", 
                "0.0"
            ], 
            [
                "1983", 
                "0.0"
            ], 
            [
                "1985", 
                "0.0"
            ], 
            [
                "1986", 
                "0.2"
            ], 
            [
                "1987", 
                "0.0"
            ], 
            [
                "1988", 
                "0.0"
            ], 
            [
                "1990", 
                "0.0"
            ], 
            [
                "1991", 
                "0.0"
            ], 
            [
                "1992", 
                "0.4"
            ], 
            [
                "1993", 
                "0.0"
            ], 
            [
                "1995", 
                "0.16666666666666666"
            ], 
            [
                "1997", 
                "0.0"
            ], 
            [
                "1998", 
                "0.0"
            ], 
            [
                "2002", 
                "0.0"
            ], 
            [
                "2004", 
                "0.0"
            ], 
            [
                "2005", 
                "0.2"
            ], 
            [
                "2006", 
                "0.0"
            ], 
            [
                "2007", 
                "0.0"
            ], 
            [
                "2008", 
                "1.0"
            ], 
            [
                "2009", 
                "0.0"
            ], 
            [
                "2010", 
                "0.0"
            ], 
            [
                "2011", 
                "0.0"
            ], 
            [
                "2012", 
                "0.0"
            ], 
            [
                "2013", 
                "0.0"
            ], 
            [
                "2014", 
                "0.0"
            ]
        ], 
        "key": "Topic 05"
    }, 
    {
        "values": [
            [
                "1976", 
                "0.8"
            ], 
            [
                "1977", 
                "1.2"
            ], 
            [
                "1978", 
                "0.0"
            ], 
            [
                "1980", 
                "0.0"
            ], 
            [
                "1981", 
                "0.0"
            ], 
            [
                "1982", 
                "0.0"
            ], 
            [
                "1983", 
                "0.0"
            ], 
            [
                "1985", 
                "0.0"
            ], 
            [
                "1986", 
                "0.8"
            ], 
            [
                "1987", 
                "0.0"
            ], 
            [
                "1988", 
                "0.0"
            ], 
            [
                "1990", 
                "0.0"
            ], 
            [
                "1991", 
                "0.0"
            ], 
            [
                "1992", 
                "0.0"
            ], 
            [
                "1993", 
                "1.0"
            ], 
            [
                "1995", 
                "0.0"
            ], 
            [
                "1997", 
                "0.2"
            ], 
            [
                "1998", 
                "0.0"
            ], 
            [
                "2002", 
                "0.0"
            ], 
            [
                "2004", 
                "0.0"
            ], 
            [
                "2005", 
                "0.8"
            ], 
            [
                "2006", 
                "0.0"
            ], 
            [
                "2007", 
                "0.0"
            ], 
            [
                "2008", 
                "0.0"
            ], 
            [
                "2009", 
                "1.0"
            ], 
            [
                "2010", 
                "0.0"
            ], 
            [
                "2011", 
                "0.0"
            ], 
            [
                "2012", 
                "0.0"
            ], 
            [
                "2013", 
                "0.0"
            ], 
            [
                "2014", 
                "0.0"
            ]
        ], 
        "key": "Topic 06"
    }, 
    {
        "values": [
            [
                "1976", 
                "0.0"
            ], 
            [
                "1977", 
                "0.0"
            ], 
            [
                "1978", 
                "0.0"
            ], 
            [
                "1980", 
                "0.0"
            ], 
            [
                "1981", 
                "0.0"
            ], 
            [
                "1982", 
                "0.8"
            ], 
            [
                "1983", 
                "0.0"
            ], 
            [
                "1985", 
                "0.0"
            ], 
            [
                "1986", 
                "0.0"
            ], 
            [
                "1987", 
                "0.0"
            ], 
            [
                "1988", 
                "0.0"
            ], 
            [
                "1990", 
                "0.2"
            ], 
            [
                "1991", 
                "0.8"
            ], 
            [
                "1992", 
                "0.0"
            ], 
            [
                "1993", 
                "0.0"
            ], 
            [
                "1995", 
                "0.0"
            ], 
            [
                "1997", 
                "0.0"
            ], 
            [
                "1998", 
                "0.0"
            ], 
            [
                "2002", 
                "0.0"
            ], 
            [
                "2004", 
                "0.0"
            ], 
            [
                "2005", 
                "0.0"
            ], 
            [
                "2006", 
                "0.0"
            ], 
            [
                "2007", 
                "0.0"
            ], 
            [
                "2008", 
                "0.0"
            ], 
            [
                "2009", 
                "0.6666666666666666"
            ], 
            [
                "2010", 
                "0.4"
            ], 
            [
                "2011", 
                "1.0"
            ], 
            [
                "2012", 
                "0.0"
            ], 
            [
                "2013", 
                "0.0"
            ], 
            [
                "2014", 
                "0.0"
            ]
        ], 
        "key": "Topic 07"
    }, 
    {
        "values": [
            [
                "1976", 
                "0.0"
            ], 
            [
                "1977", 
                "0.0"
            ], 
            [
                "1978", 
                "0.0"
            ], 
            [
                "1980", 
                "0.0"
            ], 
            [
                "1981", 
                "0.0"
            ], 
            [
                "1982", 
                "1.0"
            ], 
            [
                "1983", 
                "0.0"
            ], 
            [
                "1985", 
                "0.2"
            ], 
            [
                "1986", 
                "0.0"
            ], 
            [
                "1987", 
                "0.0"
            ], 
            [
                "1988", 
                "0.0"
            ], 
            [
                "1990", 
                "0.0"
            ], 
            [
                "1991", 
                "0.0"
            ], 
            [
                "1992", 
                "0.0"
            ], 
            [
                "1993", 
                "0.0"
            ], 
            [
                "1995", 
                "0.0"
            ], 
            [
                "1997", 
                "0.0"
            ], 
            [
                "1998", 
                "0.0"
            ], 
            [
                "2002", 
                "0.0"
            ], 
            [
                "2004", 
                "0.0"
            ], 
            [
                "2005", 
                "0.0"
            ], 
            [
                "2006", 
                "0.0"
            ], 
            [
                "2007", 
                "0.0"
            ], 
            [
                "2008", 
                "0.0"
            ], 
            [
                "2009", 
                "0.0"
            ], 
            [
                "2010", 
                "0.0"
            ], 
            [
                "2011", 
                "0.0"
            ], 
            [
                "2012", 
                "0.0"
            ], 
            [
                "2013", 
                "0.0"
            ], 
            [
                "2014", 
                "0.0"
            ]
        ], 
        "key": "Topic 08"
    }, 
    {
        "values": [
            [
                "1976", 
                "0.0"
            ], 
            [
                "1977", 
                "0.2"
            ], 
            [
                "1978", 
                "0.0"
            ], 
            [
                "1980", 
                "0.0"
            ], 
            [
                "1981", 
                "0.0"
            ], 
            [
                "1982", 
                "0.0"
            ], 
            [
                "1983", 
                "0.0"
            ], 
            [
                "1985", 
                "0.5"
            ], 
            [
                "1986", 
                "0.0"
            ], 
            [
                "1987", 
                "0.0"
            ], 
            [
                "1988", 
                "0.0"
            ], 
            [
                "1990", 
                "0.0"
            ], 
            [
                "1991", 
                "0.0"
            ], 
            [
                "1992", 
                "0.6"
            ], 
            [
                "1993", 
                "0.0"
            ], 
            [
                "1995", 
                "0.0"
            ], 
            [
                "1997", 
                "0.0"
            ], 
            [
                "1998", 
                "0.0"
            ], 
            [
                "2002", 
                "0.0"
            ], 
            [
                "2004", 
                "0.0"
            ], 
            [
                "2005", 
                "0.0"
            ], 
            [
                "2006", 
                "0.0"
            ], 
            [
                "2007", 
                "0.0"
            ], 
            [
                "2008", 
                "1.0"
            ], 
            [
                "2009", 
                "0.6666666666666666"
            ], 
            [
                "2010", 
                "0.0"
            ], 
            [
                "2011", 
                "0.0"
            ], 
            [
                "2012", 
                "0.0"
            ], 
            [
                "2013", 
                "0.0"
            ], 
            [
                "2014", 
                "0.0"
            ]
        ], 
        "key": "Topic 09"
    }, 
    {
        "values": [
            [
                "1976", 
                "0.0"
            ], 
            [
                "1977", 
                "0.0"
            ], 
            [
                "1978", 
                "0.0"
            ], 
            [
                "1980", 
                "0.0"
            ], 
            [
                "1981", 
                "0.0"
            ], 
            [
                "1982", 
                "0.8"
            ], 
            [
                "1983", 
                "0.0"
            ], 
            [
                "1985", 
                "0.0"
            ], 
            [
                "1986", 
                "0.0"
            ], 
            [
                "1987", 
                "0.0"
            ], 
            [
                "1988", 
                "0.6"
            ], 
            [
                "1990", 
                "0.0"
            ], 
            [
                "1991", 
                "0.0"
            ], 
            [
                "1992", 
                "0.0"
            ], 
            [
                "1993", 
                "0.0"
            ], 
            [
                "1995", 
                "0.16666666666666666"
            ], 
            [
                "1997", 
                "0.0"
            ], 
            [
                "1998", 
                "0.0"
            ], 
            [
                "2002", 
                "0.0"
            ], 
            [
                "2004", 
                "0.0"
            ], 
            [
                "2005", 
                "0.0"
            ], 
            [
                "2006", 
                "0.6666666666666666"
            ], 
            [
                "2007", 
                "0.0"
            ], 
            [
                "2008", 
                "0.0"
            ], 
            [
                "2009", 
                "0.0"
            ], 
            [
                "2010", 
                "0.0"
            ], 
            [
                "2011", 
                "0.0"
            ], 
            [
                "2012", 
                "0.0"
            ], 
            [
                "2013", 
                "0.0"
            ], 
            [
                "2014", 
                "0.0"
            ]
        ], 
        "key": "Topic 10"
    }, 
    {
        "values": [
            [
                "1976", 
                "0.0"
            ], 
            [
                "1977", 
                "0.0"
            ], 
            [
                "1978", 
                "0.0"
            ], 
            [
                "1980", 
                "0.0"
            ], 
            [
                "1981", 
                "0.0"
            ], 
            [
                "1982", 
                "0.0"
            ], 
            [
                "1983", 
                "0.0"
            ], 
            [
                "1985", 
                "0.0"
            ], 
            [
                "1986", 
                "0.0"
            ], 
            [
                "1987", 
                "0.0"
            ], 
            [
                "1988", 
                "0.0"
            ], 
            [
                "1990", 
                "0.0"
            ], 
            [
                "1991", 
                "0.0"
            ], 
            [
                "1992", 
                "0.0"
            ], 
            [
                "1993", 
                "0.0"
            ], 
            [
                "1995", 
                "0.0"
            ], 
            [
                "1997", 
                "0.0"
            ], 
            [
                "1998", 
                "0.2"
            ], 
            [
                "2002", 
                "0.0"
            ], 
            [
                "2004", 
                "0.6"
            ], 
            [
                "2005", 
                "0.0"
            ], 
            [
                "2006", 
                "0.3333333333333333"
            ], 
            [
                "2007", 
                "0.0"
            ], 
            [
                "2008", 
                "0.0"
            ], 
            [
                "2009", 
                "0.0"
            ], 
            [
                "2010", 
                "0.0"
            ], 
            [
                "2011", 
                "0.0"
            ], 
            [
                "2012", 
                "0.0"
            ], 
            [
                "2013", 
                "0.0"
            ], 
            [
                "2014", 
                "0.0"
            ]
        ], 
        "key": "Topic 11"
    }, 
    {
        "values": [
            [
                "1976", 
                "0.0"
            ], 
            [
                "1977", 
                "0.0"
            ], 
            [
                "1978", 
                "0.0"
            ], 
            [
                "1980", 
                "0.0"
            ], 
            [
                "1981", 
                "0.0"
            ], 
            [
                "1982", 
                "0.0"
            ], 
            [
                "1983", 
                "0.0"
            ], 
            [
                "1985", 
                "0.0"
            ], 
            [
                "1986", 
                "0.0"
            ], 
            [
                "1987", 
                "0.0"
            ], 
            [
                "1988", 
                "0.0"
            ], 
            [
                "1990", 
                "0.0"
            ], 
            [
                "1991", 
                "0.0"
            ], 
            [
                "1992", 
                "0.0"
            ], 
            [
                "1993", 
                "0.0"
            ], 
            [
                "1995", 
                "1.0"
            ], 
            [
                "1997", 
                "0.0"
            ], 
            [
                "1998", 
                "0.0"
            ], 
            [
                "2002", 
                "0.0"
            ], 
            [
                "2004", 
                "0.0"
            ], 
            [
                "2005", 
                "0.0"
            ], 
            [
                "2006", 
                "0.0"
            ], 
            [
                "2007", 
                "0.16666666666666666"
            ], 
            [
                "2008", 
                "0.3333333333333333"
            ], 
            [
                "2009", 
                "0.0"
            ], 
            [
                "2010", 
                "1.0"
            ], 
            [
                "2011", 
                "0.0"
            ], 
            [
                "2012", 
                "0.0"
            ], 
            [
                "2013", 
                "0.0"
            ], 
            [
                "2014", 
                "0.0"
            ]
        ], 
        "key": "Topic 12"
    }, 
    {
        "values": [
            [
                "1976", 
                "0.0"
            ], 
            [
                "1977", 
                "0.0"
            ], 
            [
                "1978", 
                "0.0"
            ], 
            [
                "1980", 
                "0.0"
            ], 
            [
                "1981", 
                "0.0"
            ], 
            [
                "1982", 
                "0.0"
            ], 
            [
                "1983", 
                "0.6"
            ], 
            [
                "1985", 
                "0.8"
            ], 
            [
                "1986", 
                "0.0"
            ], 
            [
                "1987", 
                "0.8571428571428571"
            ], 
            [
                "1988", 
                "0.0"
            ], 
            [
                "1990", 
                "0.0"
            ], 
            [
                "1991", 
                "0.0"
            ], 
            [
                "1992", 
                "0.0"
            ], 
            [
                "1993", 
                "0.0"
            ], 
            [
                "1995", 
                "0.0"
            ], 
            [
                "1997", 
                "0.4"
            ], 
            [
                "1998", 
                "0.0"
            ], 
            [
                "2002", 
                "0.0"
            ], 
            [
                "2004", 
                "0.0"
            ], 
            [
                "2005", 
                "0.0"
            ], 
            [
                "2006", 
                "0.0"
            ], 
            [
                "2007", 
                "0.0"
            ], 
            [
                "2008", 
                "0.0"
            ], 
            [
                "2009", 
                "0.0"
            ], 
            [
                "2010", 
                "0.0"
            ], 
            [
                "2011", 
                "0.0"
            ], 
            [
                "2012", 
                "0.0"
            ], 
            [
                "2013", 
                "0.0"
            ], 
            [
                "2014", 
                "0.0"
            ]
        ], 
        "key": "Topic 13"
    }, 
    {
        "values": [
            [
                "1976", 
                "0.0"
            ], 
            [
                "1977", 
                "0.4"
            ], 
            [
                "1978", 
                "0.0"
            ], 
            [
                "1980", 
                "0.0"
            ], 
            [
                "1981", 
                "0.0"
            ], 
            [
                "1982", 
                "0.8"
            ], 
            [
                "1983", 
                "0.0"
            ], 
            [
                "1985", 
                "0.3666666666666667"
            ], 
            [
                "1986", 
                "0.0"
            ], 
            [
                "1987", 
                "0.0"
            ], 
            [
                "1988", 
                "0.0"
            ], 
            [
                "1990", 
                "0.0"
            ], 
            [
                "1991", 
                "0.0"
            ], 
            [
                "1992", 
                "0.0"
            ], 
            [
                "1993", 
                "0.0"
            ], 
            [
                "1995", 
                "0.0"
            ], 
            [
                "1997", 
                "0.0"
            ], 
            [
                "1998", 
                "0.0"
            ], 
            [
                "2002", 
                "0.0"
            ], 
            [
                "2004", 
                "0.0"
            ], 
            [
                "2005", 
                "0.0"
            ], 
            [
                "2006", 
                "0.0"
            ], 
            [
                "2007", 
                "0.0"
            ], 
            [
                "2008", 
                "0.0"
            ], 
            [
                "2009", 
                "0.0"
            ], 
            [
                "2010", 
                "0.0"
            ], 
            [
                "2011", 
                "0.0"
            ], 
            [
                "2012", 
                "0.0"
            ], 
            [
                "2013", 
                "0.0"
            ], 
            [
                "2014", 
                "0.0"
            ]
        ], 
        "key": "Topic 14"
    }, 
    {
        "values": [
            [
                "1976", 
                "0.0"
            ], 
            [
                "1977", 
                "0.4"
            ], 
            [
                "1978", 
                "0.0"
            ], 
            [
                "1980", 
                "0.0"
            ], 
            [
                "1981", 
                "0.0"
            ], 
            [
                "1982", 
                "0.0"
            ], 
            [
                "1983", 
                "0.0"
            ], 
            [
                "1985", 
                "0.3333333333333333"
            ], 
            [
                "1986", 
                "1.0"
            ], 
            [
                "1987", 
                "0.14285714285714285"
            ], 
            [
                "1988", 
                "0.0"
            ], 
            [
                "1990", 
                "0.8"
            ], 
            [
                "1991", 
                "0.2"
            ], 
            [
                "1992", 
                "0.6"
            ], 
            [
                "1993", 
                "0.0"
            ], 
            [
                "1995", 
                "0.0"
            ], 
            [
                "1997", 
                "0.4"
            ], 
            [
                "1998", 
                "0.4"
            ], 
            [
                "2002", 
                "0.0"
            ], 
            [
                "2004", 
                "0.0"
            ], 
            [
                "2005", 
                "0.0"
            ], 
            [
                "2006", 
                "0.0"
            ], 
            [
                "2007", 
                "1.0"
            ], 
            [
                "2008", 
                "0.0"
            ], 
            [
                "2009", 
                "0.0"
            ], 
            [
                "2010", 
                "0.0"
            ], 
            [
                "2011", 
                "0.0"
            ], 
            [
                "2012", 
                "0.0"
            ], 
            [
                "2013", 
                "0.0"
            ], 
            [
                "2014", 
                "0.0"
            ]
        ], 
        "key": "Topic 15"
    }, 
    {
        "values": [
            [
                "1976", 
                "0.0"
            ], 
            [
                "1977", 
                "0.0"
            ], 
            [
                "1978", 
                "0.0"
            ], 
            [
                "1980", 
                "0.0"
            ], 
            [
                "1981", 
                "0.6"
            ], 
            [
                "1982", 
                "0.2"
            ], 
            [
                "1983", 
                "0.4"
            ], 
            [
                "1985", 
                "0.4"
            ], 
            [
                "1986", 
                "0.0"
            ], 
            [
                "1987", 
                "0.0"
            ], 
            [
                "1988", 
                "0.4"
            ], 
            [
                "1990", 
                "0.0"
            ], 
            [
                "1991", 
                "0.0"
            ], 
            [
                "1992", 
                "0.0"
            ], 
            [
                "1993", 
                "0.0"
            ], 
            [
                "1995", 
                "0.0"
            ], 
            [
                "1997", 
                "0.0"
            ], 
            [
                "1998", 
                "0.0"
            ], 
            [
                "2002", 
                "0.0"
            ], 
            [
                "2004", 
                "0.0"
            ], 
            [
                "2005", 
                "0.0"
            ], 
            [
                "2006", 
                "1.2"
            ], 
            [
                "2007", 
                "0.0"
            ], 
            [
                "2008", 
                "0.0"
            ], 
            [
                "2009", 
                "0.0"
            ], 
            [
                "2010", 
                "0.4"
            ], 
            [
                "2011", 
                "0.0"
            ], 
            [
                "2012", 
                "0.0"
            ], 
            [
                "2013", 
                "0.8571428571428571"
            ], 
            [
                "2014", 
                "0.0"
            ]
        ], 
        "key": "Topic 16"
    }, 
    {
        "values": [
            [
                "1976", 
                "0.0"
            ], 
            [
                "1977", 
                "0.0"
            ], 
            [
                "1978", 
                "0.0"
            ], 
            [
                "1980", 
                "0.0"
            ], 
            [
                "1981", 
                "0.0"
            ], 
            [
                "1982", 
                "0.0"
            ], 
            [
                "1983", 
                "0.0"
            ], 
            [
                "1985", 
                "0.0"
            ], 
            [
                "1986", 
                "0.0"
            ], 
            [
                "1987", 
                "0.0"
            ], 
            [
                "1988", 
                "0.0"
            ], 
            [
                "1990", 
                "0.0"
            ], 
            [
                "1991", 
                "0.0"
            ], 
            [
                "1992", 
                "0.0"
            ], 
            [
                "1993", 
                "1.0"
            ], 
            [
                "1995", 
                "0.0"
            ], 
            [
                "1997", 
                "1.0"
            ], 
            [
                "1998", 
                "0.4"
            ], 
            [
                "2002", 
                "0.0"
            ], 
            [
                "2004", 
                "0.0"
            ], 
            [
                "2005", 
                "0.0"
            ], 
            [
                "2006", 
                "0.0"
            ], 
            [
                "2007", 
                "0.0"
            ], 
            [
                "2008", 
                "0.0"
            ], 
            [
                "2009", 
                "0.0"
            ], 
            [
                "2010", 
                "0.0"
            ], 
            [
                "2011", 
                "0.0"
            ], 
            [
                "2012", 
                "0.0"
            ], 
            [
                "2013", 
                "0.5"
            ], 
            [
                "2014", 
                "0.0"
            ]
        ], 
        "key": "Topic 17"
    }, 
    {
        "values": [
            [
                "1976", 
                "0.0"
            ], 
            [
                "1977", 
                "0.4"
            ], 
            [
                "1978", 
                "0.0"
            ], 
            [
                "1980", 
                "0.0"
            ], 
            [
                "1981", 
                "0.0"
            ], 
            [
                "1982", 
                "0.2"
            ], 
            [
                "1983", 
                "0.4"
            ], 
            [
                "1985", 
                "0.2"
            ], 
            [
                "1986", 
                "0.0"
            ], 
            [
                "1987", 
                "0.0"
            ], 
            [
                "1988", 
                "0.0"
            ], 
            [
                "1990", 
                "0.0"
            ], 
            [
                "1991", 
                "1.0"
            ], 
            [
                "1992", 
                "0.0"
            ], 
            [
                "1993", 
                "0.0"
            ], 
            [
                "1995", 
                "0.6666666666666666"
            ], 
            [
                "1997", 
                "0.0"
            ], 
            [
                "1998", 
                "1.0"
            ], 
            [
                "2002", 
                "0.0"
            ], 
            [
                "2004", 
                "0.4"
            ], 
            [
                "2005", 
                "0.0"
            ], 
            [
                "2006", 
                "0.0"
            ], 
            [
                "2007", 
                "0.0"
            ], 
            [
                "2008", 
                "0.0"
            ], 
            [
                "2009", 
                "0.0"
            ], 
            [
                "2010", 
                "0.0"
            ], 
            [
                "2011", 
                "0.0"
            ], 
            [
                "2012", 
                "0.0"
            ], 
            [
                "2013", 
                "0.16666666666666666"
            ], 
            [
                "2014", 
                "0.0"
            ]
        ], 
        "key": "Topic 18"
    }, 
    {
        "values": [
            [
                "1976", 
                "0.0"
            ], 
            [
                "1977", 
                "0.0"
            ], 
            [
                "1978", 
                "0.0"
            ], 
            [
                "1980", 
                "0.0"
            ], 
            [
                "1981", 
                "0.0"
            ], 
            [
                "1982", 
                "0.5"
            ], 
            [
                "1983", 
                "0.0"
            ], 
            [
                "1985", 
                "0.0"
            ], 
            [
                "1986", 
                "0.0"
            ], 
            [
                "1987", 
                "0.0"
            ], 
            [
                "1988", 
                "0.0"
            ], 
            [
                "1990", 
                "0.0"
            ], 
            [
                "1991", 
                "0.0"
            ], 
            [
                "1992", 
                "0.0"
            ], 
            [
                "1993", 
                "0.0"
            ], 
            [
                "1995", 
                "0.0"
            ], 
            [
                "1997", 
                "0.0"
            ], 
            [
                "1998", 
                "0.0"
            ], 
            [
                "2002", 
                "0.0"
            ], 
            [
                "2004", 
                "0.0"
            ], 
            [
                "2005", 
                "0.0"
            ], 
            [
                "2006", 
                "0.8"
            ], 
            [
                "2007", 
                "0.0"
            ], 
            [
                "2008", 
                "0.8333333333333334"
            ], 
            [
                "2009", 
                "0.0"
            ], 
            [
                "2010", 
                "0.0"
            ], 
            [
                "2011", 
                "0.0"
            ], 
            [
                "2012", 
                "0.0"
            ], 
            [
                "2013", 
                "0.0"
            ], 
            [
                "2014", 
                "0.0"
            ]
        ], 
        "key": "Topic 19"
    }, 
    {
        "values": [
            [
                "1976", 
                "0.0"
            ], 
            [
                "1977", 
                "0.2"
            ], 
            [
                "1978", 
                "0.0"
            ], 
            [
                "1980", 
                "0.0"
            ], 
            [
                "1981", 
                "0.4"
            ], 
            [
                "1982", 
                "0.0"
            ], 
            [
                "1983", 
                "0.0"
            ], 
            [
                "1985", 
                "0.0"
            ], 
            [
                "1986", 
                "0.0"
            ], 
            [
                "1987", 
                "0.0"
            ], 
            [
                "1988", 
                "0.0"
            ], 
            [
                "1990", 
                "0.0"
            ], 
            [
                "1991", 
                "0.0"
            ], 
            [
                "1992", 
                "0.0"
            ], 
            [
                "1993", 
                "0.0"
            ], 
            [
                "1995", 
                "0.0"
            ], 
            [
                "1997", 
                "0.0"
            ], 
            [
                "1998", 
                "0.0"
            ], 
            [
                "2002", 
                "0.0"
            ], 
            [
                "2004", 
                "0.0"
            ], 
            [
                "2005", 
                "0.0"
            ], 
            [
                "2006", 
                "0.0"
            ], 
            [
                "2007", 
                "0.0"
            ], 
            [
                "2008", 
                "0.0"
            ], 
            [
                "2009", 
                "0.0"
            ], 
            [
                "2010", 
                "0.0"
            ], 
            [
                "2011", 
                "0.0"
            ], 
            [
                "2012", 
                "0.0"
            ], 
            [
                "2013", 
                "0.0"
            ], 
            [
                "2014", 
                "0.0"
            ]
        ], 
        "key": "Topic 20"
    }, 
    {
        "values": [
            [
                "1976", 
                "0.0"
            ], 
            [
                "1977", 
                "0.2"
            ], 
            [
                "1978", 
                "0.16666666666666666"
            ], 
            [
                "1980", 
                "1.0"
            ], 
            [
                "1981", 
                "0.0"
            ], 
            [
                "1982", 
                "0.0"
            ], 
            [
                "1983", 
                "1.0"
            ], 
            [
                "1985", 
                "0.2"
            ], 
            [
                "1986", 
                "0.0"
            ], 
            [
                "1987", 
                "0.0"
            ], 
            [
                "1988", 
                "0.0"
            ], 
            [
                "1990", 
                "0.0"
            ], 
            [
                "1991", 
                "1.0"
            ], 
            [
                "1992", 
                "0.0"
            ], 
            [
                "1993", 
                "0.0"
            ], 
            [
                "1995", 
                "0.0"
            ], 
            [
                "1997", 
                "0.0"
            ], 
            [
                "1998", 
                "0.0"
            ], 
            [
                "2002", 
                "0.0"
            ], 
            [
                "2004", 
                "0.0"
            ], 
            [
                "2005", 
                "0.0"
            ], 
            [
                "2006", 
                "0.0"
            ], 
            [
                "2007", 
                "0.0"
            ], 
            [
                "2008", 
                "0.16666666666666666"
            ], 
            [
                "2009", 
                "0.3333333333333333"
            ], 
            [
                "2010", 
                "0.0"
            ], 
            [
                "2011", 
                "0.0"
            ], 
            [
                "2012", 
                "0.0"
            ], 
            [
                "2013", 
                "0.0"
            ], 
            [
                "2014", 
                "0.0"
            ]
        ], 
        "key": "Topic 21"
    }
]